pygame_nevui/__init__.py
pygame_nevui/animations.py
pygame_nevui/color.py
pygame_nevui/layouts.py
pygame_nevui/menu.py
pygame_nevui/style.py
pygame_nevui/utils.py
pygame_nevui/widgets.py
pygame_nevui/window.py
pygame_nevui-0.1.2.dist-info/LICENSE
pygame_nevui-0.1.2.dist-info/METADATA
pygame_nevui-0.1.2.dist-info/WHEEL
pygame_nevui-0.1.2.dist-info/RECORD
