Metadata-Version: 2.3
Name: pygame_nevui
Version: 0.1.2
Summary: UI Library for Pygame
License: MIT
Keywords: pygame,gui,ui,interface,widgets,nevui
Author: NIKITA
Author-email: bebrovgolem@gmail.com
Requires-Python: >=3.8,<4.0
Classifier: Development Status :: 3 - Alpha
Classifier: Intended Audience :: Developers
Classifier: License :: OSI Approved :: MIT License
Classifier: Programming Language :: Python :: 3
Classifier: Programming Language :: Python :: 3.8
Classifier: Programming Language :: Python :: 3.9
Classifier: Programming Language :: Python :: 3.10
Classifier: Programming Language :: Python :: 3.11
Classifier: Programming Language :: Python :: 3.12
Classifier: Programming Language :: Python :: 3.13
Classifier: Topic :: Games/Entertainment
Classifier: Topic :: Software Development :: Libraries :: Application Frameworks
Classifier: Topic :: Software Development :: User Interfaces
Requires-Dist: Pillow (>=9.0.0,<10.0.0)
Requires-Dist: numpy (>=1.20,<2.0)
Requires-Dist: pygame (>=2.1.0)
